{"sourceSheet":"Villagers","name":"Goose","iconImage":"https://acnhcdn.com/latest/NpcIcon/chn00.png","photoImage":"https://acnhcdn.com/latest/NpcBromide/NpcNmlChn00.png","houseImage":"https://acnhcdn.com/drivesync/render/houses/chn00_89_Goose.png","species":"Chicken","gender":"Male","personality":"Jock","subtype":"B","hobby":"Fitness","birthday":"10/04","catchphrase":"buh-kay","favoriteSong":"K.K. Country","favoriteSaying":"Birds of a feather crow together.","defaultClothing":8206,"defaultUmbrella":"rainbow umbrella","wallpaper":"green painted-wood wall","flooring":"artsy parquet flooring","furnitureList":"3439;1913;3122;2605;3251;2713;3438;787;2560;3818;4123","furnitureNameList":"wooden table;wooden chair;mini DIY workbench;wooden simple bed;gas range;refrigerator;wooden end table;tape deck;wooden chest;pennant;mini-cactus set","nameColor":"#848484","bubbleColor":"#ffffff","filename":"chn00","uniqueEntryId":"5iSyoeFknLsoYManw","colors":["Blue","White"],"styles":["Simple","Active"]}