{"sourceSheet":"Villagers","name":"Lucy","iconImage":"https://acnhcdn.com/latest/NpcIcon/pig04.png","photoImage":"https://acnhcdn.com/latest/NpcBromide/NpcNmlPig04.png","houseImage":"https://acnhcdn.com/drivesync/render/houses/pig04_303_Lucy.png","species":"Pig","gender":"Female","personality":"Normal","subtype":"B","hobby":"Music","birthday":"06/02","catchphrase":"snoooink","favoriteSong":"K.K. Sonata","favoriteSaying":"The best is yet to come.","defaultClothing":4403,"defaultUmbrella":"cherry umbrella","wallpaper":"heavy-curtain wall","flooring":"wooden-knot flooring","furnitureList":"7348;7348;1875;7348;7348;3681;3958;794;7529;7529;7529;7529;1221;7527;7527","furnitureNameList":"red carpet;red carpet;grand piano;red carpet;red carpet;piano bench;antique mini table;phonograph;folding chair;folding chair;folding chair;folding chair;video camera;flower stand;flower stand","nameColor":"#848484","bubbleColor":"#ffffff","filename":"pig04","uniqueEntryId":"8FpMvE2W6YJtmTpiQ","colors":["Pink","Red"],"styles":["Cute","Elegant"]}