{"sourceSheet":"Villagers","name":"Admiral","iconImage":"https://acnhcdn.com/latest/NpcIcon/brd06.png","photoImage":"https://acnhcdn.com/latest/NpcBromide/NpcNmlBrd06.png","houseImage":"https://acnhcdn.com/drivesync/render/houses/brd06_39_Admiral.png","species":"Bird","gender":"Male","personality":"Cranky","subtype":"A","hobby":"Nature","birthday":"01/27","catchphrase":"aye aye","favoriteSong":"Steep Hill","favoriteSaying":"Only quitters give up.","defaultClothing":3164,"defaultUmbrella":"bat umbrella","wallpaper":"dirt-clod wall","flooring":"tatami","furnitureList":"717;1849;7047;2736;787;5970;3449;3622;3802;4106;3438;4029","furnitureNameList":"clay furnace;kotatsu;zen cushion;retro fan;tape deck;firewood;wooden stool;floor seat;pine bonsai tree;pendulum clock;wooden end table;rotary phone","nameColor":"#fffce9","bubbleColor":"#0ca54a","filename":"brd06","uniqueEntryId":"B3RyfNEqwGmcccRC3","colors":["Black","Blue"],"styles":["Cool","Cool"]}