{"sourceSheet":"Villagers","name":"Rizzo","iconImage":"https://acnhcdn.com/latest/NpcIcon/mus09.png","photoImage":"https://acnhcdn.com/latest/NpcBromide/NpcNmlMus09.png","houseImage":"https://acnhcdn.com/drivesync/render/houses/mus09_257_Rizzo.png","species":"Mouse","gender":"Male","personality":"Cranky","subtype":"B","hobby":"Education","birthday":"01/17","catchphrase":"squee","favoriteSong":"K.K. Folk","favoriteSaying":"Evil lurks everywhere.","defaultClothing":3460,"defaultUmbrella":"paper parasol","wallpaper":"mortar wall","flooring":"dirt flooring","furnitureList":"3580;10743;710;3692;6831;6831;3617;5978;5978","furnitureNameList":"bonsai shelf;bamboo speaker;bamboo bench;plain wooden shop sign;blossom-viewing lantern;blossom-viewing lantern;stall;bamboo lunch box;bamboo lunch box","nameColor":"#fffad4","bubbleColor":"#8bcdea","filename":"mus09","uniqueEntryId":"vmbvXTtjpswNLkcpi","colors":["Black","Gray"],"styles":["Simple","Cool"]}