{"sourceSheet":"Housewares","name":"spooky carriage","patternTitle":null,"diy":true,"patternCustomize":false,"kitType":"Pumpkin","size":"3x3","surface":false,"exchangePrice":null,"exchangeCurrency":null,"sourceNotes":null,"seasonEvent":"Halloween","seasonEventExclusive":true,"hhaBasePoints":201,"hhaCategory":null,"interact":true,"tag":"Seasonal Decor","outdoor":true,"speakerType":null,"lightingType":"Emission","catalog":"Not for sale","versionAdded":"1.5.0","unlocked":true,"set":null,"series":"spooky","customizationKitCost":7,"variants":[{"image":"https://acnhcdn.com/latest/FtrIcon/FtrHwnCarriage_Remake_0_0.png","variation":"Orange","filename":"FtrHwnCarriage_Remake_0_0","variantId":"0_0","uniqueEntryId":"ziHXyQXKhpFGh3o5W","colors":["Orange","Brown"],"pattern":null,"bodyCustomize":true,"bodyTitle":"Pumpkin color","source":["Crafting","Jack"],"internalId":4087,"buy":-1,"sell":35700,"themes":["horror"]},{"image":"https://acnhcdn.com/latest/FtrIcon/FtrHwnCarriage_Remake_1_0.png","variation":"Yellow","filename":"FtrHwnCarriage_Remake_1_0","variantId":"1_0","uniqueEntryId":"HY9CgxYGhjYpRSyhi","colors":["Yellow","Brown"],"pattern":null,"bodyCustomize":true,"bodyTitle":"Pumpkin color","source":["Crafting","Jack"],"internalId":4087,"buy":-1,"sell":35700,"themes":["horror"]},{"image":"https://acnhcdn.com/latest/FtrIcon/FtrHwnCarriage_Remake_2_0.png","variation":"Green","filename":"FtrHwnCarriage_Remake_2_0","variantId":"2_0","uniqueEntryId":"5aT3coownmPkdK8XG","colors":["Green","Beige"],"pattern":null,"bodyCustomize":true,"bodyTitle":"Pumpkin color","source":["Crafting","Jack"],"internalId":4087,"buy":-1,"sell":35700,"themes":["horror"]},{"image":"https://acnhcdn.com/latest/FtrIcon/FtrHwnCarriage_Remake_3_0.png","variation":"Monochrome","filename":"FtrHwnCarriage_Remake_3_0","variantId":"3_0","uniqueEntryId":"jcG8Jz8XvTuSNF9nJ","colors":["White","Black"],"pattern":null,"bodyCustomize":true,"bodyTitle":"Pumpkin color","source":["Crafting","Jack"],"internalId":4087,"buy":-1,"sell":35700,"themes":["horror"]}]}