{"sourceSheet":"Miscellaneous","name":"humidifier","patternTitle":null,"diy":false,"patternCustomize":false,"kitType":null,"size":"1x1","surface":false,"exchangePrice":null,"exchangeCurrency":null,"sourceNotes":"Available in the re-buyable slot in Nook's Cranny","seasonEvent":"Winter shopping","seasonEventExclusive":false,"hhaBasePoints":103,"hhaCategory":"Appliance","interact":true,"tag":"Home Appliances","outdoor":false,"speakerType":null,"lightingType":"Emission","catalog":"For sale","versionAdded":"1.0.0","unlocked":true,"set":null,"series":null,"customizationKitCost":null,"variants":[{"image":"https://acnhcdn.com/latest/FtrIcon/FtrHumidifier_Remake_0_0.png","variation":"White","filename":"FtrHumidifier_Remake_0_0","variantId":"0_0","uniqueEntryId":"scBY3NjBgm98c7Cd9","colors":["White","White"],"pattern":null,"bodyCustomize":false,"bodyTitle":null,"source":["Nook's Cranny"],"internalId":1836,"buy":1400,"sell":350,"themes":["office","living room"]},{"image":"https://acnhcdn.com/latest/FtrIcon/FtrHumidifier_Remake_1_0.png","variation":"Natural","filename":"FtrHumidifier_Remake_1_0","variantId":"1_0","uniqueEntryId":"bJTrZiusaSoLomQoJ","colors":["Beige","White"],"pattern":null,"bodyCustomize":false,"bodyTitle":null,"source":["Nook's Cranny"],"internalId":1836,"buy":1400,"sell":350,"themes":["office","living room"]},{"image":"https://acnhcdn.com/latest/FtrIcon/FtrHumidifier_Remake_2_0.png","variation":"Brown","filename":"FtrHumidifier_Remake_2_0","variantId":"2_0","uniqueEntryId":"4bQxrJ9RmDDsmtLBr","colors":["Brown","White"],"pattern":null,"bodyCustomize":false,"bodyTitle":null,"source":["Nook's Cranny"],"internalId":1836,"buy":1400,"sell":350,"themes":["office","living room"]},{"image":"https://acnhcdn.com/latest/FtrIcon/FtrHumidifier_Remake_3_0.png","variation":"Pink","filename":"FtrHumidifier_Remake_3_0","variantId":"3_0","uniqueEntryId":"nsFfDebWPqiwXpAs9","colors":["Pink","Pink"],"pattern":null,"bodyCustomize":false,"bodyTitle":null,"source":["Nook's Cranny"],"internalId":1836,"buy":1400,"sell":350,"themes":["office","living room"]},{"image":"https://acnhcdn.com/latest/FtrIcon/FtrHumidifier_Remake_4_0.png","variation":"Yellow","filename":"FtrHumidifier_Remake_4_0","variantId":"4_0","uniqueEntryId":"Ns2h96u6HXXfibyrT","colors":["Yellow","Yellow"],"pattern":null,"bodyCustomize":false,"bodyTitle":null,"source":["Nook's Cranny"],"internalId":1836,"buy":1400,"sell":350,"themes":["office","living room"]},{"image":"https://acnhcdn.com/latest/FtrIcon/FtrHumidifier_Remake_5_0.png","variation":"Green","filename":"FtrHumidifier_Remake_5_0","variantId":"5_0","uniqueEntryId":"6hWBdSQEFLbW9NLzq","colors":["Green","Green"],"pattern":null,"bodyCustomize":false,"bodyTitle":null,"source":["Nook's Cranny"],"internalId":1836,"buy":1400,"sell":350,"themes":["office","living room"]},{"image":"https://acnhcdn.com/latest/FtrIcon/FtrHumidifier_Remake_6_0.png","variation":"Blue","filename":"FtrHumidifier_Remake_6_0","variantId":"6_0","uniqueEntryId":"Nv9NjBebmFXXTnEAc","colors":["Aqua","Aqua"],"pattern":null,"bodyCustomize":false,"bodyTitle":null,"source":["Nook's Cranny"],"internalId":1836,"buy":1400,"sell":350,"themes":["office","living room"]},{"image":"https://acnhcdn.com/latest/FtrIcon/FtrHumidifier_Remake_7_0.png","variation":"Purple","filename":"FtrHumidifier_Remake_7_0","variantId":"7_0","uniqueEntryId":"exyWc3ZQXGoXMNfdE","colors":["Purple","Purple"],"pattern":null,"bodyCustomize":false,"bodyTitle":null,"source":["Nook's Cranny"],"internalId":1836,"buy":1400,"sell":350,"themes":["office","living room"]}]}