{"sourceSheet":"Housewares","name":"mush parasol","patternTitle":null,"diy":true,"patternCustomize":false,"kitType":"Normal","size":"2x2","surface":false,"exchangePrice":null,"exchangeCurrency":null,"sourceNotes":null,"seasonEvent":"mushrooms","seasonEventExclusive":true,"hhaBasePoints":201,"hhaCategory":null,"interact":false,"tag":"Plants","outdoor":true,"speakerType":null,"lightingType":null,"catalog":"Not for sale","versionAdded":"1.0.0","unlocked":true,"set":null,"series":"mush","customizationKitCost":2,"variants":[{"image":"https://acnhcdn.com/latest/FtrIcon/FtrMushroomParasol_Remake_0_0.png","variation":"Ordinary mushroom","filename":"FtrMushroomParasol_Remake_0_0","variantId":"0_0","uniqueEntryId":"YoHwDYpbfA3Q7vaaE","colors":["Orange","Brown"],"pattern":null,"bodyCustomize":true,"bodyTitle":"Mushroom type","source":["Crafting"],"internalId":3805,"buy":-1,"sell":1200,"themes":["garden"]},{"image":"https://acnhcdn.com/latest/FtrIcon/FtrMushroomParasol_Remake_1_0.png","variation":"White mushroom","filename":"FtrMushroomParasol_Remake_1_0","variantId":"1_0","uniqueEntryId":"6ysyJKh9q8GPqtmDd","colors":["White","Brown"],"pattern":null,"bodyCustomize":true,"bodyTitle":"Mushroom type","source":["Crafting"],"internalId":3805,"buy":-1,"sell":1200,"themes":["garden"]},{"image":"https://acnhcdn.com/latest/FtrIcon/FtrMushroomParasol_Remake_2_0.png","variation":"Strange mushroom","filename":"FtrMushroomParasol_Remake_2_0","variantId":"2_0","uniqueEntryId":"uiHMZyCL9Ad8Fuy4T","colors":["Gray","Brown"],"pattern":null,"bodyCustomize":true,"bodyTitle":"Mushroom type","source":["Crafting"],"internalId":3805,"buy":-1,"sell":1200,"themes":["garden"]},{"image":"https://acnhcdn.com/latest/FtrIcon/FtrMushroomParasol_Remake_3_0.png","variation":"Red mushroom","filename":"FtrMushroomParasol_Remake_3_0","variantId":"3_0","uniqueEntryId":"Qa4fYkaT8sAvitZz9","colors":["Red","Brown"],"pattern":null,"bodyCustomize":true,"bodyTitle":"Mushroom type","source":["Crafting"],"internalId":3805,"buy":-1,"sell":1200,"themes":["garden"]},{"image":"https://acnhcdn.com/latest/FtrIcon/FtrMushroomParasol_Remake_4_0.png","variation":"Yellow mushroom","filename":"FtrMushroomParasol_Remake_4_0","variantId":"4_0","uniqueEntryId":"eKdzydLdowBncibBP","colors":["Yellow","Brown"],"pattern":null,"bodyCustomize":true,"bodyTitle":"Mushroom type","source":["Crafting"],"internalId":3805,"buy":-1,"sell":1200,"themes":["garden"]}]}