{"sourceSheet":"Socks","name":"pom-pom socks","diy":false,"hhaBasePoints":51,"size":"1x1","exchangePrice":null,"exchangeCurrency":null,"sourceNotes":"Available from Able Sisters shop only","seasonEvent":"Winter shopping","seasonEventExclusive":false,"seasonalAvailability":"Winter","seasonality":"Spring","mannequinSeason":null,"gender":"Free","style1":"Cute","style2":"Cute","sortOrder":1,"villagerEquippable":false,"catalog":"For sale","versionAdded":"1.0.0","unlocked":true,"clothGroupId":611,"variants":[{"variation":"Pink","filename":"SocksTexBobble0","uniqueEntryId":"xTxpqcYovDS7R4brm","colors":["Pink","White"],"source":["Able Sisters"],"closetImage":"https://acnhcdn.com/latest/ClosetIcon/SocksTexBobble0.png","storageImage":"https://acnhcdn.com/latest/FtrIcon/SocksTexBobble0.png","internalId":5179,"labelThemes":["everyday","fairy tale","comfy"],"buy":720,"sell":180,"themes":[]},{"variation":"Orange","filename":"SocksTexBobble3","uniqueEntryId":"7cX6yDzovZqcytqYq","colors":["Orange","White"],"source":["Able Sisters"],"closetImage":"https://acnhcdn.com/latest/ClosetIcon/SocksTexBobble3.png","storageImage":"https://acnhcdn.com/latest/FtrIcon/SocksTexBobble3.png","internalId":9074,"labelThemes":["everyday","fairy tale","comfy"],"buy":720,"sell":180,"themes":[]},{"variation":"Green","filename":"SocksTexBobble2","uniqueEntryId":"sJ4i4vbxAsffiM4PS","colors":["Green","White"],"source":["Able Sisters"],"closetImage":"https://acnhcdn.com/latest/ClosetIcon/SocksTexBobble2.png","storageImage":"https://acnhcdn.com/latest/FtrIcon/SocksTexBobble2.png","internalId":9073,"labelThemes":["everyday","fairy tale","comfy"],"buy":720,"sell":180,"themes":[]},{"variation":"Blue","filename":"SocksTexBobble1","uniqueEntryId":"X2Esyxf48CNDo7aS5","colors":["Aqua","White"],"source":["Able Sisters"],"closetImage":"https://acnhcdn.com/latest/ClosetIcon/SocksTexBobble1.png","storageImage":"https://acnhcdn.com/latest/FtrIcon/SocksTexBobble1.png","internalId":9072,"labelThemes":["everyday","fairy tale","comfy"],"buy":720,"sell":180,"themes":[]},{"variation":"Purple","filename":"SocksTexBobble4","uniqueEntryId":"p8pAsGdvNt3MhZJvQ","colors":["Purple","White"],"source":["Able Sisters"],"closetImage":"https://acnhcdn.com/latest/ClosetIcon/SocksTexBobble4.png","storageImage":"https://acnhcdn.com/latest/FtrIcon/SocksTexBobble4.png","internalId":9075,"labelThemes":["everyday","fairy tale","comfy"],"buy":720,"sell":180,"themes":[]}]}