{"sourceSheet":"Other","name":"red wrapping paper","diy":false,"stackSize":10,"exchangePrice":null,"exchangeCurrency":null,"sourceNotes":null,"seasonEvent":null,"seasonEventExclusive":null,"hhaBasePoints":0,"tag":null,"versionAdded":"1.0.0","unlocked":true,"inventoryFilename":"WPaperRed","storageFilename":"WPaperRed","variants":[{"filename":"WPaperRed","uniqueEntryId":"AN7s2Q67gmpxy89Tv","colors":[],"source":["Nook's Cranny"],"storageImage":"https://acnhcdn.com/latest/FtrIcon/WPaperRed.png","internalId":7694,"buy":160,"sell":40,"themes":[],"inventoryImage":"https://acnhcdn.com/latest/MenuIcon/WPaperRed.png"}]}