{"sourceSheet":"Tops","name":"anorak jacket","diy":false,"hhaBasePoints":51,"size":"1x1","exchangePrice":null,"exchangeCurrency":null,"sourceNotes":"Available from either Mabel's temporary shop or Able Sisters shop","seasonEvent":null,"seasonEventExclusive":null,"seasonalAvailability":"All Year","seasonality":"Autumn","mannequinSeason":null,"gender":"Free","villagerGender":"Free","style1":"Simple","style2":"Cool","sortOrder":1,"villagerEquippable":true,"catalog":"For sale","versionAdded":"1.0.0","unlocked":true,"clothGroupId":548,"variants":[{"variation":"Red","filename":"TopsTexTopCoatLAnorak1","uniqueEntryId":"Ws4vh3dya8i8nPtJ9","colors":["Red","Red"],"source":["Able Sisters"],"closetImage":"https://acnhcdn.com/latest/ClosetIcon/TopsTexTopCoatLAnorak1.png","storageImage":"https://acnhcdn.com/latest/FtrIcon/TopsTexTopCoatLAnorak1.png","internalId":9308,"labelThemes":["everyday","outdoorsy"],"buy":1400,"sell":350,"themes":[]},{"variation":"Blue","filename":"TopsTexTopCoatLAnorak2","uniqueEntryId":"BaiWuWNL9muLeYYkQ","colors":["Blue","Blue"],"source":["Able Sisters"],"closetImage":"https://acnhcdn.com/latest/ClosetIcon/TopsTexTopCoatLAnorak2.png","storageImage":"https://acnhcdn.com/latest/FtrIcon/TopsTexTopCoatLAnorak2.png","internalId":9309,"labelThemes":["everyday","outdoorsy"],"buy":1400,"sell":350,"themes":[]},{"variation":"Camel","filename":"TopsTexTopCoatLAnorak0","uniqueEntryId":"agpR79ZTHcuQheDdF","colors":["Beige","Beige"],"source":["Able Sisters"],"closetImage":"https://acnhcdn.com/latest/ClosetIcon/TopsTexTopCoatLAnorak0.png","storageImage":"https://acnhcdn.com/latest/FtrIcon/TopsTexTopCoatLAnorak0.png","internalId":4793,"labelThemes":["everyday","outdoorsy"],"buy":1400,"sell":350,"themes":[]}]}