{"sourceSheet":"Wall-mounted","name":"heart doorplate","patternTitle":null,"diy":false,"patternCustomize":false,"kitType":null,"exchangePrice":null,"exchangeCurrency":null,"size":"1x1","sourceNotes":"Available in Nook's Cranny (either upgrade tier) in the unique furniture slot","seasonEvent":null,"seasonEventExclusive":null,"hhaBasePoints":151,"hhaCategory":null,"interact":false,"tag":"House Door Decor","outdoor":false,"lightingType":null,"doorDeco":true,"catalog":"For sale","versionAdded":"1.0.0","unlocked":true,"set":null,"series":null,"customizationKitCost":null,"variants":[{"image":"https://acnhcdn.com/latest/FtrIcon/FtrDoorOrnamentPlateHeart_Remake_0_0.png","variation":"Pink","filename":"FtrDoorOrnamentPlateHeart_Remake_0_0","variantId":"0_0","uniqueEntryId":"Lmtub5DdFXrXgoR6D","colors":["Pink","White"],"pattern":null,"bodyCustomize":false,"bodyTitle":null,"source":["Nook's Cranny"],"internalId":5309,"buy":600,"sell":150,"themes":["fancy"]},{"image":"https://acnhcdn.com/latest/FtrIcon/FtrDoorOrnamentPlateHeart_Remake_1_0.png","variation":"Blue","filename":"FtrDoorOrnamentPlateHeart_Remake_1_0","variantId":"1_0","uniqueEntryId":"LvwnwvwwpPczdTuLq","colors":["Gray","Aqua"],"pattern":null,"bodyCustomize":false,"bodyTitle":null,"source":["Nook's Cranny"],"internalId":5309,"buy":600,"sell":150,"themes":["fancy"]},{"image":"https://acnhcdn.com/latest/FtrIcon/FtrDoorOrnamentPlateHeart_Remake_2_0.png","variation":"Monotone","filename":"FtrDoorOrnamentPlateHeart_Remake_2_0","variantId":"2_0","uniqueEntryId":"q8wjLxhoLce4xsRWs","colors":["Black","White"],"pattern":null,"bodyCustomize":false,"bodyTitle":null,"source":["Nook's Cranny"],"internalId":5309,"buy":600,"sell":150,"themes":["fancy"]},{"image":"https://acnhcdn.com/latest/FtrIcon/FtrDoorOrnamentPlateHeart_Remake_3_0.png","variation":"Light blue","filename":"FtrDoorOrnamentPlateHeart_Remake_3_0","variantId":"3_0","uniqueEntryId":"AK6iwJsbkvSBCLANE","colors":["Blue","Aqua"],"pattern":null,"bodyCustomize":false,"bodyTitle":null,"source":["Nook's Cranny"],"internalId":5309,"buy":600,"sell":150,"themes":["fancy"]},{"image":"https://acnhcdn.com/latest/FtrIcon/FtrDoorOrnamentPlateHeart_Remake_4_0.png","variation":"Green","filename":"FtrDoorOrnamentPlateHeart_Remake_4_0","variantId":"4_0","uniqueEntryId":"gCZ4KFisK2Chq9vx9","colors":["Green","Green"],"pattern":null,"bodyCustomize":false,"bodyTitle":null,"source":["Nook's Cranny"],"internalId":5309,"buy":600,"sell":150,"themes":["fancy"]},{"image":"https://acnhcdn.com/latest/FtrIcon/FtrDoorOrnamentPlateHeart_Remake_5_0.png","variation":"Orange","filename":"FtrDoorOrnamentPlateHeart_Remake_5_0","variantId":"5_0","uniqueEntryId":"bHkYXbik6E39oNo86","colors":["Orange","Orange"],"pattern":null,"bodyCustomize":false,"bodyTitle":null,"source":["Nook's Cranny"],"internalId":5309,"buy":600,"sell":150,"themes":["fancy"]},{"image":"https://acnhcdn.com/latest/FtrIcon/FtrDoorOrnamentPlateHeart_Remake_6_0.png","variation":"Red","filename":"FtrDoorOrnamentPlateHeart_Remake_6_0","variantId":"6_0","uniqueEntryId":"bgXr3xzPreLGin9wf","colors":["Red","Red"],"pattern":null,"bodyCustomize":false,"bodyTitle":null,"source":["Nook's Cranny"],"internalId":5309,"buy":600,"sell":150,"themes":["fancy"]},{"image":"https://acnhcdn.com/latest/FtrIcon/FtrDoorOrnamentPlateHeart_Remake_7_0.png","variation":"Purple","filename":"FtrDoorOrnamentPlateHeart_Remake_7_0","variantId":"7_0","uniqueEntryId":"3Ax6LuJdM5swHE5iL","colors":["Purple","Purple"],"pattern":null,"bodyCustomize":false,"bodyTitle":null,"source":["Nook's Cranny"],"internalId":5309,"buy":600,"sell":150,"themes":["fancy"]}]}