{"sourceSheet":"Wallpaper","name":"ice wall","vfx":true,"vfxType":null,"diy":true,"exchangePrice":null,"exchangeCurrency":null,"sourceNotes":null,"seasonEvent":"snowflakes","seasonEventExclusive":true,"windowType":null,"windowColor":null,"paneType":null,"curtainType":null,"curtainColor":null,"ceilingType":"Stone","hhaBasePoints":444,"tag":"Special Walls","catalog":"Not for sale","versionAdded":"1.0.0","unlocked":true,"series":"frozen","variants":[{"image":"https://acnhcdn.com/latest/FtrIcon/RoomSpWallIce00.png","filename":"RoomSpWallIce00","uniqueEntryId":"d84Y3R4CzrtjCasov","colors":["Aqua","Aqua"],"source":["Crafting"],"internalId":5505,"buy":-1,"sell":8200,"themes":["freezing cold","facility"]}]}