{"sourceSheet":"Other","name":"delivery","diy":false,"stackSize":1,"exchangePrice":null,"exchangeCurrency":null,"sourceNotes":null,"seasonEvent":null,"seasonEventExclusive":null,"hhaBasePoints":0,"tag":null,"versionAdded":"1.0.0","unlocked":true,"inventoryFilename":"Cardboard","storageFilename":null,"variants":[{"filename":"DummyCardboard","uniqueEntryId":"dSEW4GQniyS8P6SnE","colors":[],"source":["Nook Shopping"],"storageImage":null,"internalId":4645,"buy":-1,"sell":null,"themes":[],"inventoryImage":"https://acnhcdn.com/latest/MenuIcon/Cardboard.png"}]}