{"sourceSheet":"Shoes","name":"sporty sandals","diy":false,"hhaBasePoints":51,"size":"1x1","exchangePrice":null,"exchangeCurrency":null,"sourceNotes":"Available from Able Sisters shop only","seasonEvent":null,"seasonEventExclusive":null,"seasonalAvailability":"All Year","seasonality":"Summer","mannequinSeason":null,"gender":"Free","style1":"Active","style2":"Active","sortOrder":1,"villagerEquippable":false,"catalog":"For sale","versionAdded":"1.0.0","unlocked":true,"clothGroupId":894,"variants":[{"variation":"Red","filename":"ShoesSandalSports0","uniqueEntryId":"dB9Zh49MxmTnhe2sT","colors":["Red","Black"],"source":["Able Sisters"],"closetImage":"https://acnhcdn.com/latest/ClosetIcon/ShoesSandalSports0.png","storageImage":"https://acnhcdn.com/latest/FtrIcon/ShoesSandalSports0.png","internalId":5824,"labelThemes":["outdoorsy","comfy","sporty","vacation"],"buy":1300,"sell":325,"themes":[]},{"variation":"Pink","filename":"ShoesSandalSports5","uniqueEntryId":"cFDQtHvQLzvDxXBmF","colors":["Pink","Black"],"source":["Able Sisters"],"closetImage":"https://acnhcdn.com/latest/ClosetIcon/ShoesSandalSports5.png","storageImage":"https://acnhcdn.com/latest/FtrIcon/ShoesSandalSports5.png","internalId":10732,"labelThemes":["outdoorsy","comfy","sporty","vacation"],"buy":1300,"sell":325,"themes":[]},{"variation":"Olive","filename":"ShoesSandalSports1","uniqueEntryId":"vvY85zikpeYg4Y2bh","colors":["Green","Black"],"source":["Able Sisters"],"closetImage":"https://acnhcdn.com/latest/ClosetIcon/ShoesSandalSports1.png","storageImage":"https://acnhcdn.com/latest/FtrIcon/ShoesSandalSports1.png","internalId":10728,"labelThemes":["outdoorsy","comfy","sporty","vacation"],"buy":1300,"sell":325,"themes":[]},{"variation":"Green","filename":"ShoesSandalSports4","uniqueEntryId":"DAkrAkhrWzoLCghmY","colors":["Green","Black"],"source":["Able Sisters"],"closetImage":"https://acnhcdn.com/latest/ClosetIcon/ShoesSandalSports4.png","storageImage":"https://acnhcdn.com/latest/FtrIcon/ShoesSandalSports4.png","internalId":10731,"labelThemes":["outdoorsy","comfy","sporty","vacation"],"buy":1300,"sell":325,"themes":[]},{"variation":"Gray","filename":"ShoesSandalSports7","uniqueEntryId":"FtBvM9FNfSW2YkvR4","colors":["Aqua","Black"],"source":["Able Sisters"],"closetImage":"https://acnhcdn.com/latest/ClosetIcon/ShoesSandalSports7.png","storageImage":"https://acnhcdn.com/latest/FtrIcon/ShoesSandalSports7.png","internalId":10734,"labelThemes":["outdoorsy","comfy","sporty","vacation"],"buy":1300,"sell":325,"themes":[]},{"variation":"Blue","filename":"ShoesSandalSports2","uniqueEntryId":"fjn8jpqyKCATL5Zrj","colors":["Blue","Black"],"source":["Able Sisters"],"closetImage":"https://acnhcdn.com/latest/ClosetIcon/ShoesSandalSports2.png","storageImage":"https://acnhcdn.com/latest/FtrIcon/ShoesSandalSports2.png","internalId":10729,"labelThemes":["outdoorsy","comfy","sporty","vacation"],"buy":1300,"sell":325,"themes":[]},{"variation":"Purple","filename":"ShoesSandalSports3","uniqueEntryId":"NPRvY4itdRnthXiXb","colors":["Purple","Black"],"source":["Able Sisters"],"closetImage":"https://acnhcdn.com/latest/ClosetIcon/ShoesSandalSports3.png","storageImage":"https://acnhcdn.com/latest/FtrIcon/ShoesSandalSports3.png","internalId":10730,"labelThemes":["outdoorsy","comfy","sporty","vacation"],"buy":1300,"sell":325,"themes":[]},{"variation":"Beige","filename":"ShoesSandalSports6","uniqueEntryId":"gHXQ5sakxYkDn3fAP","colors":["Beige","Black"],"source":["Able Sisters"],"closetImage":"https://acnhcdn.com/latest/ClosetIcon/ShoesSandalSports6.png","storageImage":"https://acnhcdn.com/latest/FtrIcon/ShoesSandalSports6.png","internalId":10733,"labelThemes":["outdoorsy","comfy","sporty","vacation"],"buy":1300,"sell":325,"themes":[]}]}