{"sourceSheet":"Other","name":"tailors moving kit","diy":false,"stackSize":1,"exchangePrice":null,"exchangeCurrency":null,"sourceNotes":null,"seasonEvent":null,"seasonEventExclusive":null,"hhaBasePoints":0,"tag":null,"versionAdded":"1.0.0","unlocked":true,"inventoryFilename":"TentWhite","storageFilename":null,"variants":[{"filename":"MovingKitTailor","uniqueEntryId":"GaNHE6Zd7QJtFKMwW","colors":[],"source":["Tom Nook"],"storageImage":null,"internalId":5359,"buy":-1,"sell":null,"themes":[],"inventoryImage":"https://acnhcdn.com/latest/MenuIcon/TentWhite.png"}]}