{"sourceSheet":"Floors","name":"bamboo flooring","vfx":false,"diy":true,"exchangePrice":null,"exchangeCurrency":null,"sourceNotes":null,"seasonEvent":null,"seasonEventExclusive":null,"hhaBasePoints":103,"tag":"Nature - Green","catalog":"Not for sale","versionAdded":"1.0.0","unlocked":true,"series":"bamboo","variants":[{"image":"https://acnhcdn.com/latest/FtrIcon/RoomTexFloorBamboo00.png","filename":"RoomTexFloorBamboo00","uniqueEntryId":"gMeLjZdPobbrt58sT","colors":["Green","Beige"],"source":["Crafting"],"internalId":4964,"buy":-1,"sell":2400,"themes":["zen-style"]}]}