{"sourceSheet":"Shoes","name":"flower sandals","diy":false,"hhaBasePoints":51,"size":"1x1","exchangePrice":null,"exchangeCurrency":null,"sourceNotes":"Available from Able Sisters shop only","seasonEvent":"Summer shopping","seasonEventExclusive":false,"seasonalAvailability":"Summer","seasonality":"All Year","mannequinSeason":"Summer","gender":"Free","style1":"Cute","style2":"Cute","sortOrder":1,"villagerEquippable":false,"catalog":"For sale","versionAdded":"1.0.0","unlocked":true,"clothGroupId":766,"variants":[{"variation":"White","filename":"ShoesSandalFlower6","uniqueEntryId":"zEAdQCRGCGkGXo3zH","colors":["White","Gray"],"source":["Able Sisters"],"closetImage":"https://acnhcdn.com/latest/ClosetIcon/ShoesSandalFlower6.png","storageImage":"https://acnhcdn.com/latest/FtrIcon/ShoesSandalFlower6.png","internalId":10131,"labelThemes":["fairy tale","outdoorsy","vacation"],"buy":1200,"sell":300,"themes":[]},{"variation":"Black","filename":"ShoesSandalFlower5","uniqueEntryId":"sZKDexuZQqMHvKNha","colors":["Black","Gray"],"source":["Able Sisters"],"closetImage":"https://acnhcdn.com/latest/ClosetIcon/ShoesSandalFlower5.png","storageImage":"https://acnhcdn.com/latest/FtrIcon/ShoesSandalFlower5.png","internalId":10130,"labelThemes":["fairy tale","outdoorsy","vacation"],"buy":1200,"sell":300,"themes":[]},{"variation":"Pink","filename":"ShoesSandalFlower1","uniqueEntryId":"CuM8H6yjAxM9hvKbB","colors":["Red","Pink"],"source":["Able Sisters"],"closetImage":"https://acnhcdn.com/latest/ClosetIcon/ShoesSandalFlower1.png","storageImage":"https://acnhcdn.com/latest/FtrIcon/ShoesSandalFlower1.png","internalId":10126,"labelThemes":["fairy tale","outdoorsy","vacation"],"buy":1200,"sell":300,"themes":[]},{"variation":"Yellow","filename":"ShoesSandalFlower0","uniqueEntryId":"iKjt4fpKTzWFNoWqv","colors":["Yellow","White"],"source":["Able Sisters"],"closetImage":"https://acnhcdn.com/latest/ClosetIcon/ShoesSandalFlower0.png","storageImage":"https://acnhcdn.com/latest/FtrIcon/ShoesSandalFlower0.png","internalId":5475,"labelThemes":["fairy tale","outdoorsy","vacation"],"buy":1200,"sell":300,"themes":[]},{"variation":"Green","filename":"ShoesSandalFlower2","uniqueEntryId":"MvQdXTd5fpze9DrcN","colors":["Green","Green"],"source":["Able Sisters"],"closetImage":"https://acnhcdn.com/latest/ClosetIcon/ShoesSandalFlower2.png","storageImage":"https://acnhcdn.com/latest/FtrIcon/ShoesSandalFlower2.png","internalId":10127,"labelThemes":["fairy tale","outdoorsy","vacation"],"buy":1200,"sell":300,"themes":[]},{"variation":"Blue","filename":"ShoesSandalFlower4","uniqueEntryId":"iBZH8z7aReKctqLyG","colors":["Blue","Aqua"],"source":["Able Sisters"],"closetImage":"https://acnhcdn.com/latest/ClosetIcon/ShoesSandalFlower4.png","storageImage":"https://acnhcdn.com/latest/FtrIcon/ShoesSandalFlower4.png","internalId":10129,"labelThemes":["fairy tale","outdoorsy","vacation"],"buy":1200,"sell":300,"themes":[]},{"variation":"Purple","filename":"ShoesSandalFlower3","uniqueEntryId":"vMQexjCj2Egq6S9Tm","colors":["Purple","Purple"],"source":["Able Sisters"],"closetImage":"https://acnhcdn.com/latest/ClosetIcon/ShoesSandalFlower3.png","storageImage":"https://acnhcdn.com/latest/FtrIcon/ShoesSandalFlower3.png","internalId":10128,"labelThemes":["fairy tale","outdoorsy","vacation"],"buy":1200,"sell":300,"themes":[]}]}