{"sourceSheet":"Housewares","name":"changing room","patternTitle":"Curtain","diy":false,"patternCustomize":true,"kitType":"Normal","size":"1x1","surface":false,"exchangePrice":null,"exchangeCurrency":null,"sourceNotes":"Available in Nook's Cranny (upgraded only), in the unique furniture slot","seasonEvent":null,"seasonEventExclusive":null,"hhaBasePoints":151,"hhaCategory":null,"interact":"Wardrobe","tag":"Shop","outdoor":false,"speakerType":null,"lightingType":null,"catalog":"For sale","versionAdded":"1.0.0","unlocked":true,"set":null,"series":null,"customizationKitCost":2,"variants":[{"image":"https://acnhcdn.com/latest/FtrIcon/FtrFittingroom_Remake_0_0.png","variation":"Gray","filename":"FtrFittingroom_Remake_0_0","variantId":"0_0","uniqueEntryId":"7AgotMN5NwbjAmjNQ","colors":["White","White"],"pattern":"White","bodyCustomize":false,"bodyTitle":null,"source":["Nook's Cranny"],"internalId":1816,"buy":3700,"sell":925,"themes":["shop","facility"]},{"image":"https://acnhcdn.com/latest/FtrIcon/FtrFittingroom_Remake_0_1.png","variation":"Gray","filename":"FtrFittingroom_Remake_0_1","variantId":"0_1","uniqueEntryId":"ix23xBZAgkNvgMz37","colors":["White","Purple"],"pattern":"Purple","bodyCustomize":false,"bodyTitle":null,"source":["Nook's Cranny"],"internalId":1816,"buy":3700,"sell":925,"themes":["shop","facility"]},{"image":"https://acnhcdn.com/latest/FtrIcon/FtrFittingroom_Remake_0_2.png","variation":"Gray","filename":"FtrFittingroom_Remake_0_2","variantId":"0_2","uniqueEntryId":"SRCSi2JJhquLSCZ8e","colors":["White","Black"],"pattern":"Black","bodyCustomize":false,"bodyTitle":null,"source":["Nook's Cranny"],"internalId":1816,"buy":3700,"sell":925,"themes":["shop","facility"]},{"image":"https://acnhcdn.com/latest/FtrIcon/FtrFittingroom_Remake_0_3.png","variation":"Gray","filename":"FtrFittingroom_Remake_0_3","variantId":"0_3","uniqueEntryId":"5LF7kvq2vx6t9WNvz","colors":["White","Yellow"],"pattern":"Yellow","bodyCustomize":false,"bodyTitle":null,"source":["Nook's Cranny"],"internalId":1816,"buy":3700,"sell":925,"themes":["shop","facility"]},{"image":"https://acnhcdn.com/latest/FtrIcon/FtrFittingroom_Remake_0_4.png","variation":"Gray","filename":"FtrFittingroom_Remake_0_4","variantId":"0_4","uniqueEntryId":"GkLpRsYjKtNT6rMKW","colors":["White","Pink"],"pattern":"Pink","bodyCustomize":false,"bodyTitle":null,"source":["Nook's Cranny"],"internalId":1816,"buy":3700,"sell":925,"themes":["shop","facility"]},{"image":"https://acnhcdn.com/latest/FtrIcon/FtrFittingroom_Remake_0_5.png","variation":"Gray","filename":"FtrFittingroom_Remake_0_5","variantId":"0_5","uniqueEntryId":"4aRrQYq57rDxJkesF","colors":["White","Red"],"pattern":"Red","bodyCustomize":false,"bodyTitle":null,"source":["Nook's Cranny"],"internalId":1816,"buy":3700,"sell":925,"themes":["shop","facility"]},{"image":"https://acnhcdn.com/latest/FtrIcon/FtrFittingroom_Remake_0_6.png","variation":"Gray","filename":"FtrFittingroom_Remake_0_6","variantId":"0_6","uniqueEntryId":"YMxucW7KzNz6NqmWp","colors":["White","Green"],"pattern":"Green","bodyCustomize":false,"bodyTitle":null,"source":["Nook's Cranny"],"internalId":1816,"buy":3700,"sell":925,"themes":["shop","facility"]},{"image":"https://acnhcdn.com/latest/FtrIcon/FtrFittingroom_Remake_0_7.png","variation":"Gray","filename":"FtrFittingroom_Remake_0_7","variantId":"0_7","uniqueEntryId":"x37RGuHrDjMtvGnj5","colors":["White","Aqua"],"pattern":"Blue","bodyCustomize":false,"bodyTitle":null,"source":["Nook's Cranny"],"internalId":1816,"buy":3700,"sell":925,"themes":["shop","facility"]},{"image":"https://acnhcdn.com/latest/FtrIcon/FtrFittingroom_Remake_1_0.png","variation":"Beige","filename":"FtrFittingroom_Remake_1_0","variantId":"1_0","uniqueEntryId":"HC78zjnDvoFo8gaNK","colors":["Yellow","White"],"pattern":"White","bodyCustomize":false,"bodyTitle":null,"source":["Nook's Cranny"],"internalId":1816,"buy":3700,"sell":925,"themes":["shop","facility"]},{"image":"https://acnhcdn.com/latest/FtrIcon/FtrFittingroom_Remake_1_1.png","variation":"Beige","filename":"FtrFittingroom_Remake_1_1","variantId":"1_1","uniqueEntryId":"9TyMiWTo8XgkRbipQ","colors":["Yellow","Purple"],"pattern":"Purple","bodyCustomize":false,"bodyTitle":null,"source":["Nook's Cranny"],"internalId":1816,"buy":3700,"sell":925,"themes":["shop","facility"]},{"image":"https://acnhcdn.com/latest/FtrIcon/FtrFittingroom_Remake_1_2.png","variation":"Beige","filename":"FtrFittingroom_Remake_1_2","variantId":"1_2","uniqueEntryId":"qHL9ohFPfgs4HZdrb","colors":["Yellow","Black"],"pattern":"Black","bodyCustomize":false,"bodyTitle":null,"source":["Nook's Cranny"],"internalId":1816,"buy":3700,"sell":925,"themes":["shop","facility"]},{"image":"https://acnhcdn.com/latest/FtrIcon/FtrFittingroom_Remake_1_3.png","variation":"Beige","filename":"FtrFittingroom_Remake_1_3","variantId":"1_3","uniqueEntryId":"HHFZSHj9TKwgbyxSZ","colors":["Yellow","Yellow"],"pattern":"Yellow","bodyCustomize":false,"bodyTitle":null,"source":["Nook's Cranny"],"internalId":1816,"buy":3700,"sell":925,"themes":["shop","facility"]},{"image":"https://acnhcdn.com/latest/FtrIcon/FtrFittingroom_Remake_1_4.png","variation":"Beige","filename":"FtrFittingroom_Remake_1_4","variantId":"1_4","uniqueEntryId":"NPSJ8SLN6pEWWjLs2","colors":["Yellow","Pink"],"pattern":"Pink","bodyCustomize":false,"bodyTitle":null,"source":["Nook's Cranny"],"internalId":1816,"buy":3700,"sell":925,"themes":["shop","facility"]},{"image":"https://acnhcdn.com/latest/FtrIcon/FtrFittingroom_Remake_1_5.png","variation":"Beige","filename":"FtrFittingroom_Remake_1_5","variantId":"1_5","uniqueEntryId":"KcXaGW49HwocRBvzj","colors":["Yellow","Red"],"pattern":"Red","bodyCustomize":false,"bodyTitle":null,"source":["Nook's Cranny"],"internalId":1816,"buy":3700,"sell":925,"themes":["shop","facility"]},{"image":"https://acnhcdn.com/latest/FtrIcon/FtrFittingroom_Remake_1_6.png","variation":"Beige","filename":"FtrFittingroom_Remake_1_6","variantId":"1_6","uniqueEntryId":"5sR6zTAe9PsMcZkpn","colors":["Yellow","Green"],"pattern":"Green","bodyCustomize":false,"bodyTitle":null,"source":["Nook's Cranny"],"internalId":1816,"buy":3700,"sell":925,"themes":["shop","facility"]},{"image":"https://acnhcdn.com/latest/FtrIcon/FtrFittingroom_Remake_1_7.png","variation":"Beige","filename":"FtrFittingroom_Remake_1_7","variantId":"1_7","uniqueEntryId":"8oWjcCYKdLuAmDkNX","colors":["Yellow","Aqua"],"pattern":"Blue","bodyCustomize":false,"bodyTitle":null,"source":["Nook's Cranny"],"internalId":1816,"buy":3700,"sell":925,"themes":["shop","facility"]},{"image":"https://acnhcdn.com/latest/FtrIcon/FtrFittingroom_Remake_2_0.png","variation":"Brown","filename":"FtrFittingroom_Remake_2_0","variantId":"2_0","uniqueEntryId":"s3rtd7w4a4ky6JkAe","colors":["Orange","White"],"pattern":"White","bodyCustomize":false,"bodyTitle":null,"source":["Nook's Cranny"],"internalId":1816,"buy":3700,"sell":925,"themes":["shop","facility"]},{"image":"https://acnhcdn.com/latest/FtrIcon/FtrFittingroom_Remake_2_1.png","variation":"Brown","filename":"FtrFittingroom_Remake_2_1","variantId":"2_1","uniqueEntryId":"BmTLWo9YRFvGmQFdK","colors":["Orange","Purple"],"pattern":"Purple","bodyCustomize":false,"bodyTitle":null,"source":["Nook's Cranny"],"internalId":1816,"buy":3700,"sell":925,"themes":["shop","facility"]},{"image":"https://acnhcdn.com/latest/FtrIcon/FtrFittingroom_Remake_2_2.png","variation":"Brown","filename":"FtrFittingroom_Remake_2_2","variantId":"2_2","uniqueEntryId":"k3t55AoYzTC95inHh","colors":["Orange","Black"],"pattern":"Black","bodyCustomize":false,"bodyTitle":null,"source":["Nook's Cranny"],"internalId":1816,"buy":3700,"sell":925,"themes":["shop","facility"]},{"image":"https://acnhcdn.com/latest/FtrIcon/FtrFittingroom_Remake_2_3.png","variation":"Brown","filename":"FtrFittingroom_Remake_2_3","variantId":"2_3","uniqueEntryId":"jtW7atCYG4MFzjjoH","colors":["Orange","Yellow"],"pattern":"Yellow","bodyCustomize":false,"bodyTitle":null,"source":["Nook's Cranny"],"internalId":1816,"buy":3700,"sell":925,"themes":["shop","facility"]},{"image":"https://acnhcdn.com/latest/FtrIcon/FtrFittingroom_Remake_2_4.png","variation":"Brown","filename":"FtrFittingroom_Remake_2_4","variantId":"2_4","uniqueEntryId":"t3PqQ3hcZ7kLXFMt2","colors":["Orange","Pink"],"pattern":"Pink","bodyCustomize":false,"bodyTitle":null,"source":["Nook's Cranny"],"internalId":1816,"buy":3700,"sell":925,"themes":["shop","facility"]},{"image":"https://acnhcdn.com/latest/FtrIcon/FtrFittingroom_Remake_2_5.png","variation":"Brown","filename":"FtrFittingroom_Remake_2_5","variantId":"2_5","uniqueEntryId":"dbFPyRHSv7PSBbxYm","colors":["Orange","Red"],"pattern":"Red","bodyCustomize":false,"bodyTitle":null,"source":["Nook's Cranny"],"internalId":1816,"buy":3700,"sell":925,"themes":["shop","facility"]},{"image":"https://acnhcdn.com/latest/FtrIcon/FtrFittingroom_Remake_2_6.png","variation":"Brown","filename":"FtrFittingroom_Remake_2_6","variantId":"2_6","uniqueEntryId":"akZy4YmBLk8ETzBZR","colors":["Orange","Green"],"pattern":"Green","bodyCustomize":false,"bodyTitle":null,"source":["Nook's Cranny"],"internalId":1816,"buy":3700,"sell":925,"themes":["shop","facility"]},{"image":"https://acnhcdn.com/latest/FtrIcon/FtrFittingroom_Remake_2_7.png","variation":"Brown","filename":"FtrFittingroom_Remake_2_7","variantId":"2_7","uniqueEntryId":"rPWmGac8peyAiXo9n","colors":["Orange","Aqua"],"pattern":"Blue","bodyCustomize":false,"bodyTitle":null,"source":["Nook's Cranny"],"internalId":1816,"buy":3700,"sell":925,"themes":["shop","facility"]},{"image":"https://acnhcdn.com/latest/FtrIcon/FtrFittingroom_Remake_3_0.png","variation":"Dark brown","filename":"FtrFittingroom_Remake_3_0","variantId":"3_0","uniqueEntryId":"T3Sq38zLfr5LxhkQL","colors":["Brown","White"],"pattern":"White","bodyCustomize":false,"bodyTitle":null,"source":["Nook's Cranny"],"internalId":1816,"buy":3700,"sell":925,"themes":["shop","facility"]},{"image":"https://acnhcdn.com/latest/FtrIcon/FtrFittingroom_Remake_3_1.png","variation":"Dark brown","filename":"FtrFittingroom_Remake_3_1","variantId":"3_1","uniqueEntryId":"aPu342SNxYFn8CfuJ","colors":["Brown","Purple"],"pattern":"Purple","bodyCustomize":false,"bodyTitle":null,"source":["Nook's Cranny"],"internalId":1816,"buy":3700,"sell":925,"themes":["shop","facility"]},{"image":"https://acnhcdn.com/latest/FtrIcon/FtrFittingroom_Remake_3_2.png","variation":"Dark brown","filename":"FtrFittingroom_Remake_3_2","variantId":"3_2","uniqueEntryId":"3dFxBfCwKfc6Qf4sk","colors":["Brown","Black"],"pattern":"Black","bodyCustomize":false,"bodyTitle":null,"source":["Nook's Cranny"],"internalId":1816,"buy":3700,"sell":925,"themes":["shop","facility"]},{"image":"https://acnhcdn.com/latest/FtrIcon/FtrFittingroom_Remake_3_3.png","variation":"Dark brown","filename":"FtrFittingroom_Remake_3_3","variantId":"3_3","uniqueEntryId":"JPviijww3dMcTiSqv","colors":["Brown","Yellow"],"pattern":"Yellow","bodyCustomize":false,"bodyTitle":null,"source":["Nook's Cranny"],"internalId":1816,"buy":3700,"sell":925,"themes":["shop","facility"]},{"image":"https://acnhcdn.com/latest/FtrIcon/FtrFittingroom_Remake_3_4.png","variation":"Dark brown","filename":"FtrFittingroom_Remake_3_4","variantId":"3_4","uniqueEntryId":"cQ2G6AawfmoCrZhGW","colors":["Brown","Pink"],"pattern":"Pink","bodyCustomize":false,"bodyTitle":null,"source":["Nook's Cranny"],"internalId":1816,"buy":3700,"sell":925,"themes":["shop","facility"]},{"image":"https://acnhcdn.com/latest/FtrIcon/FtrFittingroom_Remake_3_5.png","variation":"Dark brown","filename":"FtrFittingroom_Remake_3_5","variantId":"3_5","uniqueEntryId":"okuEz5tc6JoST7KyC","colors":["Brown","Red"],"pattern":"Red","bodyCustomize":false,"bodyTitle":null,"source":["Nook's Cranny"],"internalId":1816,"buy":3700,"sell":925,"themes":["shop","facility"]},{"image":"https://acnhcdn.com/latest/FtrIcon/FtrFittingroom_Remake_3_6.png","variation":"Dark brown","filename":"FtrFittingroom_Remake_3_6","variantId":"3_6","uniqueEntryId":"TuEo85hZGTKmhF8Ti","colors":["Brown","Green"],"pattern":"Green","bodyCustomize":false,"bodyTitle":null,"source":["Nook's Cranny"],"internalId":1816,"buy":3700,"sell":925,"themes":["shop","facility"]},{"image":"https://acnhcdn.com/latest/FtrIcon/FtrFittingroom_Remake_3_7.png","variation":"Dark brown","filename":"FtrFittingroom_Remake_3_7","variantId":"3_7","uniqueEntryId":"4EtKRhoEjoPyxpMsB","colors":["Brown","Aqua"],"pattern":"Blue","bodyCustomize":false,"bodyTitle":null,"source":["Nook's Cranny"],"internalId":1816,"buy":3700,"sell":925,"themes":["shop","facility"]},{"image":"https://acnhcdn.com/latest/FtrIcon/FtrFittingroom_Remake_4_0.png","variation":"Black","filename":"FtrFittingroom_Remake_4_0","variantId":"4_0","uniqueEntryId":"SRDQjDatcaYRfDfm6","colors":["Black","White"],"pattern":"White","bodyCustomize":false,"bodyTitle":null,"source":["Nook's Cranny"],"internalId":1816,"buy":3700,"sell":925,"themes":["shop","facility"]},{"image":"https://acnhcdn.com/latest/FtrIcon/FtrFittingroom_Remake_4_1.png","variation":"Black","filename":"FtrFittingroom_Remake_4_1","variantId":"4_1","uniqueEntryId":"FrfbchYxYejDNhdfs","colors":["Black","Purple"],"pattern":"Purple","bodyCustomize":false,"bodyTitle":null,"source":["Nook's Cranny"],"internalId":1816,"buy":3700,"sell":925,"themes":["shop","facility"]},{"image":"https://acnhcdn.com/latest/FtrIcon/FtrFittingroom_Remake_4_2.png","variation":"Black","filename":"FtrFittingroom_Remake_4_2","variantId":"4_2","uniqueEntryId":"WxywpCh64irnyem5c","colors":["Black","Black"],"pattern":"Black","bodyCustomize":false,"bodyTitle":null,"source":["Nook's Cranny"],"internalId":1816,"buy":3700,"sell":925,"themes":["shop","facility"]},{"image":"https://acnhcdn.com/latest/FtrIcon/FtrFittingroom_Remake_4_3.png","variation":"Black","filename":"FtrFittingroom_Remake_4_3","variantId":"4_3","uniqueEntryId":"7ZFbpAqaYgdww3JWc","colors":["Black","Yellow"],"pattern":"Yellow","bodyCustomize":false,"bodyTitle":null,"source":["Nook's Cranny"],"internalId":1816,"buy":3700,"sell":925,"themes":["shop","facility"]},{"image":"https://acnhcdn.com/latest/FtrIcon/FtrFittingroom_Remake_4_4.png","variation":"Black","filename":"FtrFittingroom_Remake_4_4","variantId":"4_4","uniqueEntryId":"ED9RaoFGMEr6trrtW","colors":["Black","Pink"],"pattern":"Pink","bodyCustomize":false,"bodyTitle":null,"source":["Nook's Cranny"],"internalId":1816,"buy":3700,"sell":925,"themes":["shop","facility"]},{"image":"https://acnhcdn.com/latest/FtrIcon/FtrFittingroom_Remake_4_5.png","variation":"Black","filename":"FtrFittingroom_Remake_4_5","variantId":"4_5","uniqueEntryId":"ojMJyxybGMKHfT3NL","colors":["Black","Red"],"pattern":"Red","bodyCustomize":false,"bodyTitle":null,"source":["Nook's Cranny"],"internalId":1816,"buy":3700,"sell":925,"themes":["shop","facility"]},{"image":"https://acnhcdn.com/latest/FtrIcon/FtrFittingroom_Remake_4_6.png","variation":"Black","filename":"FtrFittingroom_Remake_4_6","variantId":"4_6","uniqueEntryId":"tbo33Z2LABD7wBoLi","colors":["Black","Green"],"pattern":"Green","bodyCustomize":false,"bodyTitle":null,"source":["Nook's Cranny"],"internalId":1816,"buy":3700,"sell":925,"themes":["shop","facility"]},{"image":"https://acnhcdn.com/latest/FtrIcon/FtrFittingroom_Remake_4_7.png","variation":"Black","filename":"FtrFittingroom_Remake_4_7","variantId":"4_7","uniqueEntryId":"LPLixYMcZctmRHZo6","colors":["Black","Aqua"],"pattern":"Blue","bodyCustomize":false,"bodyTitle":null,"source":["Nook's Cranny"],"internalId":1816,"buy":3700,"sell":925,"themes":["shop","facility"]},{"image":"https://acnhcdn.com/latest/FtrIcon/FtrFittingroom_Remake_5_0.png","variation":"Blue","filename":"FtrFittingroom_Remake_5_0","variantId":"5_0","uniqueEntryId":"9NcRAwMhgZQhSmTKA","colors":["Blue","White"],"pattern":"White","bodyCustomize":false,"bodyTitle":null,"source":["Nook's Cranny"],"internalId":1816,"buy":3700,"sell":925,"themes":["shop","facility"]},{"image":"https://acnhcdn.com/latest/FtrIcon/FtrFittingroom_Remake_5_1.png","variation":"Blue","filename":"FtrFittingroom_Remake_5_1","variantId":"5_1","uniqueEntryId":"PFDKfsfZvHBWmR4rh","colors":["Blue","Purple"],"pattern":"Purple","bodyCustomize":false,"bodyTitle":null,"source":["Nook's Cranny"],"internalId":1816,"buy":3700,"sell":925,"themes":["shop","facility"]},{"image":"https://acnhcdn.com/latest/FtrIcon/FtrFittingroom_Remake_5_2.png","variation":"Blue","filename":"FtrFittingroom_Remake_5_2","variantId":"5_2","uniqueEntryId":"tf7tuJbkg6QRvZLiQ","colors":["Blue","Black"],"pattern":"Black","bodyCustomize":false,"bodyTitle":null,"source":["Nook's Cranny"],"internalId":1816,"buy":3700,"sell":925,"themes":["shop","facility"]},{"image":"https://acnhcdn.com/latest/FtrIcon/FtrFittingroom_Remake_5_3.png","variation":"Blue","filename":"FtrFittingroom_Remake_5_3","variantId":"5_3","uniqueEntryId":"KaE9hHGdHEG5a4ZXB","colors":["Blue","Yellow"],"pattern":"Yellow","bodyCustomize":false,"bodyTitle":null,"source":["Nook's Cranny"],"internalId":1816,"buy":3700,"sell":925,"themes":["shop","facility"]},{"image":"https://acnhcdn.com/latest/FtrIcon/FtrFittingroom_Remake_5_4.png","variation":"Blue","filename":"FtrFittingroom_Remake_5_4","variantId":"5_4","uniqueEntryId":"RGoKqruNBwP9ptwhD","colors":["Blue","Pink"],"pattern":"Pink","bodyCustomize":false,"bodyTitle":null,"source":["Nook's Cranny"],"internalId":1816,"buy":3700,"sell":925,"themes":["shop","facility"]},{"image":"https://acnhcdn.com/latest/FtrIcon/FtrFittingroom_Remake_5_5.png","variation":"Blue","filename":"FtrFittingroom_Remake_5_5","variantId":"5_5","uniqueEntryId":"e2Ay6Er66ZKGsxQq8","colors":["Blue","Red"],"pattern":"Red","bodyCustomize":false,"bodyTitle":null,"source":["Nook's Cranny"],"internalId":1816,"buy":3700,"sell":925,"themes":["shop","facility"]},{"image":"https://acnhcdn.com/latest/FtrIcon/FtrFittingroom_Remake_5_6.png","variation":"Blue","filename":"FtrFittingroom_Remake_5_6","variantId":"5_6","uniqueEntryId":"P9WrpxcjWbSE2tMff","colors":["Blue","Green"],"pattern":"Green","bodyCustomize":false,"bodyTitle":null,"source":["Nook's Cranny"],"internalId":1816,"buy":3700,"sell":925,"themes":["shop","facility"]},{"image":"https://acnhcdn.com/latest/FtrIcon/FtrFittingroom_Remake_5_7.png","variation":"Blue","filename":"FtrFittingroom_Remake_5_7","variantId":"5_7","uniqueEntryId":"AnJMEYY3Sq8ztgZLr","colors":["Blue","Aqua"],"pattern":"Blue","bodyCustomize":false,"bodyTitle":null,"source":["Nook's Cranny"],"internalId":1816,"buy":3700,"sell":925,"themes":["shop","facility"]},{"image":"https://acnhcdn.com/latest/FtrIcon/FtrFittingroom_Remake_6_0.png","variation":"Pink","filename":"FtrFittingroom_Remake_6_0","variantId":"6_0","uniqueEntryId":"L4YAHZFQDr5oqbgr9","colors":["Pink","White"],"pattern":"White","bodyCustomize":false,"bodyTitle":null,"source":["Nook's Cranny"],"internalId":1816,"buy":3700,"sell":925,"themes":["shop","facility"]},{"image":"https://acnhcdn.com/latest/FtrIcon/FtrFittingroom_Remake_6_1.png","variation":"Pink","filename":"FtrFittingroom_Remake_6_1","variantId":"6_1","uniqueEntryId":"CTDPimSvents862wR","colors":["Pink","Purple"],"pattern":"Purple","bodyCustomize":false,"bodyTitle":null,"source":["Nook's Cranny"],"internalId":1816,"buy":3700,"sell":925,"themes":["shop","facility"]},{"image":"https://acnhcdn.com/latest/FtrIcon/FtrFittingroom_Remake_6_2.png","variation":"Pink","filename":"FtrFittingroom_Remake_6_2","variantId":"6_2","uniqueEntryId":"khYcTbLxFCNyQW6NY","colors":["Pink","Black"],"pattern":"Black","bodyCustomize":false,"bodyTitle":null,"source":["Nook's Cranny"],"internalId":1816,"buy":3700,"sell":925,"themes":["shop","facility"]},{"image":"https://acnhcdn.com/latest/FtrIcon/FtrFittingroom_Remake_6_3.png","variation":"Pink","filename":"FtrFittingroom_Remake_6_3","variantId":"6_3","uniqueEntryId":"bf5ixLR4teRzNPv7n","colors":["Pink","Yellow"],"pattern":"Yellow","bodyCustomize":false,"bodyTitle":null,"source":["Nook's Cranny"],"internalId":1816,"buy":3700,"sell":925,"themes":["shop","facility"]},{"image":"https://acnhcdn.com/latest/FtrIcon/FtrFittingroom_Remake_6_4.png","variation":"Pink","filename":"FtrFittingroom_Remake_6_4","variantId":"6_4","uniqueEntryId":"3m4ss2vhuXb8xuPJJ","colors":["Pink","Pink"],"pattern":"Pink","bodyCustomize":false,"bodyTitle":null,"source":["Nook's Cranny"],"internalId":1816,"buy":3700,"sell":925,"themes":["shop","facility"]},{"image":"https://acnhcdn.com/latest/FtrIcon/FtrFittingroom_Remake_6_5.png","variation":"Pink","filename":"FtrFittingroom_Remake_6_5","variantId":"6_5","uniqueEntryId":"dt9Xyquyvv5hDKkva","colors":["Pink","Red"],"pattern":"Red","bodyCustomize":false,"bodyTitle":null,"source":["Nook's Cranny"],"internalId":1816,"buy":3700,"sell":925,"themes":["shop","facility"]},{"image":"https://acnhcdn.com/latest/FtrIcon/FtrFittingroom_Remake_6_6.png","variation":"Pink","filename":"FtrFittingroom_Remake_6_6","variantId":"6_6","uniqueEntryId":"Qe2XjBGw5rPJubnd7","colors":["Pink","Green"],"pattern":"Green","bodyCustomize":false,"bodyTitle":null,"source":["Nook's Cranny"],"internalId":1816,"buy":3700,"sell":925,"themes":["shop","facility"]},{"image":"https://acnhcdn.com/latest/FtrIcon/FtrFittingroom_Remake_6_7.png","variation":"Pink","filename":"FtrFittingroom_Remake_6_7","variantId":"6_7","uniqueEntryId":"3xfiSatMq2oznqATL","colors":["Pink","Aqua"],"pattern":"Blue","bodyCustomize":false,"bodyTitle":null,"source":["Nook's Cranny"],"internalId":1816,"buy":3700,"sell":925,"themes":["shop","facility"]},{"image":"https://acnhcdn.com/latest/FtrIcon/FtrFittingroom_Remake_7_0.png","variation":"Green","filename":"FtrFittingroom_Remake_7_0","variantId":"7_0","uniqueEntryId":"oXnHqjdPy8h67dBNA","colors":["Aqua","White"],"pattern":"White","bodyCustomize":false,"bodyTitle":null,"source":["Nook's Cranny"],"internalId":1816,"buy":3700,"sell":925,"themes":["shop","facility"]},{"image":"https://acnhcdn.com/latest/FtrIcon/FtrFittingroom_Remake_7_1.png","variation":"Green","filename":"FtrFittingroom_Remake_7_1","variantId":"7_1","uniqueEntryId":"9Fh8KaoZoZk3X5fdh","colors":["Aqua","Purple"],"pattern":"Purple","bodyCustomize":false,"bodyTitle":null,"source":["Nook's Cranny"],"internalId":1816,"buy":3700,"sell":925,"themes":["shop","facility"]},{"image":"https://acnhcdn.com/latest/FtrIcon/FtrFittingroom_Remake_7_2.png","variation":"Green","filename":"FtrFittingroom_Remake_7_2","variantId":"7_2","uniqueEntryId":"PcYFdZMzmNBquo6G4","colors":["Aqua","Black"],"pattern":"Black","bodyCustomize":false,"bodyTitle":null,"source":["Nook's Cranny"],"internalId":1816,"buy":3700,"sell":925,"themes":["shop","facility"]},{"image":"https://acnhcdn.com/latest/FtrIcon/FtrFittingroom_Remake_7_3.png","variation":"Green","filename":"FtrFittingroom_Remake_7_3","variantId":"7_3","uniqueEntryId":"Tp6zrKyinYeBiTXPi","colors":["Aqua","Yellow"],"pattern":"Yellow","bodyCustomize":false,"bodyTitle":null,"source":["Nook's Cranny"],"internalId":1816,"buy":3700,"sell":925,"themes":["shop","facility"]},{"image":"https://acnhcdn.com/latest/FtrIcon/FtrFittingroom_Remake_7_4.png","variation":"Green","filename":"FtrFittingroom_Remake_7_4","variantId":"7_4","uniqueEntryId":"3QmXoP3kpPnpc7iyh","colors":["Aqua","Pink"],"pattern":"Pink","bodyCustomize":false,"bodyTitle":null,"source":["Nook's Cranny"],"internalId":1816,"buy":3700,"sell":925,"themes":["shop","facility"]},{"image":"https://acnhcdn.com/latest/FtrIcon/FtrFittingroom_Remake_7_5.png","variation":"Green","filename":"FtrFittingroom_Remake_7_5","variantId":"7_5","uniqueEntryId":"QAtdxb27ZvSBLs6r3","colors":["Aqua","Red"],"pattern":"Red","bodyCustomize":false,"bodyTitle":null,"source":["Nook's Cranny"],"internalId":1816,"buy":3700,"sell":925,"themes":["shop","facility"]},{"image":"https://acnhcdn.com/latest/FtrIcon/FtrFittingroom_Remake_7_6.png","variation":"Green","filename":"FtrFittingroom_Remake_7_6","variantId":"7_6","uniqueEntryId":"p3kGt6hYz7vGyZnM9","colors":["Aqua","Green"],"pattern":"Green","bodyCustomize":false,"bodyTitle":null,"source":["Nook's Cranny"],"internalId":1816,"buy":3700,"sell":925,"themes":["shop","facility"]},{"image":"https://acnhcdn.com/latest/FtrIcon/FtrFittingroom_Remake_7_7.png","variation":"Green","filename":"FtrFittingroom_Remake_7_7","variantId":"7_7","uniqueEntryId":"rTLYHFcFnnLAxY9yp","colors":["Aqua","Aqua"],"pattern":"Blue","bodyCustomize":false,"bodyTitle":null,"source":["Nook's Cranny"],"internalId":1816,"buy":3700,"sell":925,"themes":["shop","facility"]}]}