{"sourceSheet":"Floors","name":"rosewood flooring","vfx":false,"diy":false,"exchangePrice":null,"exchangeCurrency":null,"sourceNotes":null,"seasonEvent":null,"seasonEventExclusive":null,"hhaBasePoints":151,"tag":"Wood Floors","catalog":"For sale","versionAdded":"1.0.0","unlocked":true,"series":null,"variants":[{"image":"https://acnhcdn.com/latest/FtrIcon/RoomTexFloorRoseWood00.png","filename":"RoomTexFloorRoseWood00","uniqueEntryId":"jA7bCaTtZq6Z2r4gr","colors":["Gray","Gray"],"source":["Nook's Cranny"],"internalId":5063,"buy":2420,"sell":605,"themes":["expensive","living room"]}]}