{"sourceSheet":"Housewares","name":"mush lamp","patternTitle":null,"diy":true,"patternCustomize":false,"kitType":"Normal","size":"1x1","surface":false,"exchangePrice":null,"exchangeCurrency":null,"sourceNotes":null,"seasonEvent":"mushrooms","seasonEventExclusive":true,"hhaBasePoints":201,"hhaCategory":"Lighting","interact":true,"tag":"Lamp","outdoor":true,"speakerType":null,"lightingType":"Fluorescent","catalog":"Not for sale","versionAdded":"1.0.0","unlocked":true,"set":null,"series":"mush","customizationKitCost":3,"variants":[{"image":"https://acnhcdn.com/latest/FtrIcon/FtrMushroomLamp_Remake_0_0.png","variation":"Ordinary mushroom","filename":"FtrMushroomLamp_Remake_0_0","variantId":"0_0","uniqueEntryId":"GKFnaHSs6d9MDNttQ","colors":["Brown","Brown"],"pattern":null,"bodyCustomize":true,"bodyTitle":"Mushroom type","source":["Crafting"],"internalId":805,"buy":-1,"sell":1600,"themes":["garden"]},{"image":"https://acnhcdn.com/latest/FtrIcon/FtrMushroomLamp_Remake_1_0.png","variation":"White mushroom","filename":"FtrMushroomLamp_Remake_1_0","variantId":"1_0","uniqueEntryId":"S3qFAPAvvgv4g3DRh","colors":["White","White"],"pattern":null,"bodyCustomize":true,"bodyTitle":"Mushroom type","source":["Crafting"],"internalId":805,"buy":-1,"sell":1600,"themes":["garden"]},{"image":"https://acnhcdn.com/latest/FtrIcon/FtrMushroomLamp_Remake_2_0.png","variation":"Strange mushroom","filename":"FtrMushroomLamp_Remake_2_0","variantId":"2_0","uniqueEntryId":"JDdSXrPcPKbiQmamP","colors":["Blue","Blue"],"pattern":null,"bodyCustomize":true,"bodyTitle":"Mushroom type","source":["Crafting"],"internalId":805,"buy":-1,"sell":1600,"themes":["garden"]},{"image":"https://acnhcdn.com/latest/FtrIcon/FtrMushroomLamp_Remake_3_0.png","variation":"Red mushroom","filename":"FtrMushroomLamp_Remake_3_0","variantId":"3_0","uniqueEntryId":"cAfehsTrveDSZ6AJ2","colors":["Red","Beige"],"pattern":null,"bodyCustomize":true,"bodyTitle":"Mushroom type","source":["Crafting"],"internalId":805,"buy":-1,"sell":1600,"themes":["garden"]},{"image":"https://acnhcdn.com/latest/FtrIcon/FtrMushroomLamp_Remake_4_0.png","variation":"Yellow mushroom","filename":"FtrMushroomLamp_Remake_4_0","variantId":"4_0","uniqueEntryId":"75rpYquohgtznCDTt","colors":["Yellow","Yellow"],"pattern":null,"bodyCustomize":true,"bodyTitle":"Mushroom type","source":["Crafting"],"internalId":805,"buy":-1,"sell":1600,"themes":["garden"]}]}