{"sourceSheet":"Other","name":"Ultimate Pocket Stuffing","diy":false,"stackSize":1,"exchangePrice":8000,"exchangeCurrency":"Nook Miles","sourceNotes":null,"seasonEvent":null,"seasonEventExclusive":null,"hhaBasePoints":0,"tag":null,"versionAdded":"1.0.0","unlocked":true,"inventoryFilename":"HowtoBookExpansion","storageFilename":null,"variants":[{"filename":"HowtoBookPocketExpansion2","uniqueEntryId":"jLHd4JDRQDRxBhE9o","colors":[],"source":["Nook Miles Redemption"],"storageImage":null,"internalId":11140,"buy":-1,"sell":null,"themes":[],"inventoryImage":"https://acnhcdn.com/latest/MenuIcon/HowtoBookExpansion.png"}]}