{"sourceSheet":"Housewares","name":"playground gym","patternTitle":null,"diy":false,"patternCustomize":false,"kitType":null,"size":"2x2","surface":false,"exchangePrice":3000,"exchangeCurrency":"Nook Miles","sourceNotes":null,"seasonEvent":null,"seasonEventExclusive":null,"hhaBasePoints":103,"hhaCategory":null,"interact":true,"tag":"Playground","outdoor":true,"speakerType":null,"lightingType":null,"catalog":"Not for sale","versionAdded":"1.0.0","unlocked":true,"set":null,"series":null,"customizationKitCost":null,"variants":[{"image":"https://acnhcdn.com/latest/FtrIcon/FtrJunglegym_Remake_0_0.png","variation":"Colorful","filename":"FtrJunglegym_Remake_0_0","variantId":"0_0","uniqueEntryId":"MbEZKWwfNgEno7wWX","colors":["Colorful","Colorful"],"pattern":null,"bodyCustomize":false,"bodyTitle":null,"source":["Nook Miles Redemption"],"internalId":3430,"buy":-1,"sell":15000,"themes":["garden","child's room"]},{"image":"https://acnhcdn.com/latest/FtrIcon/FtrJunglegym_Remake_1_0.png","variation":"Monotone","filename":"FtrJunglegym_Remake_1_0","variantId":"1_0","uniqueEntryId":"vFA7baPXr6jXrNuom","colors":["White","Black"],"pattern":null,"bodyCustomize":false,"bodyTitle":null,"source":["Nook Miles Redemption"],"internalId":3430,"buy":-1,"sell":15000,"themes":["garden","child's room"]},{"image":"https://acnhcdn.com/latest/FtrIcon/FtrJunglegym_Remake_2_0.png","variation":"Red","filename":"FtrJunglegym_Remake_2_0","variantId":"2_0","uniqueEntryId":"S8JMKB7zQvsuuvaHW","colors":["Red","Yellow"],"pattern":null,"bodyCustomize":false,"bodyTitle":null,"source":["Nook Miles Redemption"],"internalId":3430,"buy":-1,"sell":15000,"themes":["garden","child's room"]},{"image":"https://acnhcdn.com/latest/FtrIcon/FtrJunglegym_Remake_3_0.png","variation":"Blue","filename":"FtrJunglegym_Remake_3_0","variantId":"3_0","uniqueEntryId":"kLfKg7kRMR8GCcJ86","colors":["Blue","Aqua"],"pattern":null,"bodyCustomize":false,"bodyTitle":null,"source":["Nook Miles Redemption"],"internalId":3430,"buy":-1,"sell":15000,"themes":["garden","child's room"]},{"image":"https://acnhcdn.com/latest/FtrIcon/FtrJunglegym_Remake_4_0.png","variation":"Green","filename":"FtrJunglegym_Remake_4_0","variantId":"4_0","uniqueEntryId":"YkdEJvZHbzXHZwSNo","colors":["Aqua","Yellow"],"pattern":null,"bodyCustomize":false,"bodyTitle":null,"source":["Nook Miles Redemption"],"internalId":3430,"buy":-1,"sell":15000,"themes":["garden","child's room"]}]}