{"sourceSheet":"Floors","name":"parking flooring","vfx":false,"diy":false,"exchangePrice":null,"exchangeCurrency":null,"sourceNotes":null,"seasonEvent":null,"seasonEventExclusive":null,"hhaBasePoints":451,"tag":"Sidewalk","catalog":"Not for sale","versionAdded":"1.0.0","unlocked":true,"series":null,"variants":[{"image":"https://acnhcdn.com/latest/FtrIcon/RoomTexFloorParking00.png","filename":"RoomTexFloorParking00","uniqueEntryId":"Lx2JZuP8F6xS28PPG","colors":["Black","Gray"],"source":["Saharah"],"internalId":4997,"buy":3000,"sell":750,"themes":["facility"]}]}