{"sourceSheet":"Bottoms","name":"ski pants","diy":false,"hhaBasePoints":51,"size":"1x1","sourceNotes":"Available from Able Sisters shop only","seasonEvent":"Winter shopping","seasonEventExclusive":false,"seasonalAvailability":"Winter","seasonality":"Winter","mannequinSeason":null,"gender":"Free","style1":"Active","style2":"Active","sortOrder":1,"villagerEquippable":false,"catalog":"For sale","versionAdded":"1.0.0","unlocked":true,"clothGroupId":374,"variants":[{"variation":"Ruby red","filename":"BottomsTexPantsWideSki2","uniqueEntryId":"nDiGP8wp2Zrsxbqnt","colors":["Pink","Purple"],"source":["Able Sisters"],"closetImage":"https://acnhcdn.com/latest/ClosetIcon/BottomsTexPantsWideSki2.png","storageImage":"https://acnhcdn.com/latest/FtrIcon/BottomsTexPantsWideSki2.png","internalId":11408,"labelThemes":["outdoorsy","sporty"],"buy":1560,"sell":390,"themes":[]},{"variation":"Red","filename":"BottomsTexPantsWideSki1","uniqueEntryId":"D4QQiQZNBmEs4ZBp4","colors":["Orange","Aqua"],"source":["Able Sisters"],"closetImage":"https://acnhcdn.com/latest/ClosetIcon/BottomsTexPantsWideSki1.png","storageImage":"https://acnhcdn.com/latest/FtrIcon/BottomsTexPantsWideSki1.png","internalId":11407,"labelThemes":["outdoorsy","sporty"],"buy":1560,"sell":390,"themes":[]},{"variation":"Yellow","filename":"BottomsTexPantsWideSki5","uniqueEntryId":"MXkckHi2iqMPvo9JN","colors":["Yellow","Pink"],"source":["Able Sisters"],"closetImage":"https://acnhcdn.com/latest/ClosetIcon/BottomsTexPantsWideSki5.png","storageImage":"https://acnhcdn.com/latest/FtrIcon/BottomsTexPantsWideSki5.png","internalId":11411,"labelThemes":["outdoorsy","sporty"],"buy":1560,"sell":390,"themes":[]},{"variation":"Turquoise","filename":"BottomsTexPantsWideSki0","uniqueEntryId":"veCodAXXupKXyHvW2","colors":["Green","Blue"],"source":["Able Sisters"],"closetImage":"https://acnhcdn.com/latest/ClosetIcon/BottomsTexPantsWideSki0.png","storageImage":"https://acnhcdn.com/latest/FtrIcon/BottomsTexPantsWideSki0.png","internalId":4450,"labelThemes":["outdoorsy","sporty"],"buy":1560,"sell":390,"themes":[]},{"variation":"Light blue","filename":"BottomsTexPantsWideSki4","uniqueEntryId":"7r5tu9eNC49zqu69c","colors":["Aqua","Red"],"source":["Able Sisters"],"closetImage":"https://acnhcdn.com/latest/ClosetIcon/BottomsTexPantsWideSki4.png","storageImage":"https://acnhcdn.com/latest/FtrIcon/BottomsTexPantsWideSki4.png","internalId":11410,"labelThemes":["outdoorsy","sporty"],"buy":1560,"sell":390,"themes":[]},{"variation":"Blue","filename":"BottomsTexPantsWideSki3","uniqueEntryId":"Qh9i4Py67kRJM9uEu","colors":["Blue","Green"],"source":["Able Sisters"],"closetImage":"https://acnhcdn.com/latest/ClosetIcon/BottomsTexPantsWideSki3.png","storageImage":"https://acnhcdn.com/latest/FtrIcon/BottomsTexPantsWideSki3.png","internalId":11409,"labelThemes":["outdoorsy","sporty"],"buy":1560,"sell":390,"themes":[]}]}