{"sourceSheet":"Tools","name":"fishing rod","diy":true,"customize":true,"uses":30,"stackSize":1,"hhaBasePoints":0,"size":"1x1","exchangePrice":null,"exchangeCurrency":null,"sourceNotes":null,"seasonEvent":null,"seasonEventExclusive":null,"versionAdded":"1.0.0","unlocked":true,"customizationKitCost":1,"variants":[{"image":"https://acnhcdn.com/latest/FtrIcon/ToolAngling_Remake_0_0.png","variation":"Blue","filename":"ToolAngling_Remake_0_0","variantId":"0_0","uniqueEntryId":"Y62px4Jy5vaMtN46u","colors":[],"bodyTitle":"Color","source":["Crafting"],"internalId":2377,"buy":-1,"sell":600,"themes":[]},{"image":"https://acnhcdn.com/latest/FtrIcon/ToolAngling_Remake_1_0.png","variation":"Yellow","filename":"ToolAngling_Remake_1_0","variantId":"1_0","uniqueEntryId":"JLMypnErvJc6n9wS8","colors":[],"bodyTitle":"Color","source":["Crafting"],"internalId":2377,"buy":-1,"sell":600,"themes":[]},{"image":"https://acnhcdn.com/latest/FtrIcon/ToolAngling_Remake_2_0.png","variation":"Green","filename":"ToolAngling_Remake_2_0","variantId":"2_0","uniqueEntryId":"WTqWoAYMKuJsXjWWv","colors":[],"bodyTitle":"Color","source":["Crafting"],"internalId":2377,"buy":-1,"sell":600,"themes":[]},{"image":"https://acnhcdn.com/latest/FtrIcon/ToolAngling_Remake_3_0.png","variation":"Red","filename":"ToolAngling_Remake_3_0","variantId":"3_0","uniqueEntryId":"SWX3JZeySqWz8PKQi","colors":[],"bodyTitle":"Color","source":["Crafting"],"internalId":2377,"buy":-1,"sell":600,"themes":[]},{"image":"https://acnhcdn.com/latest/FtrIcon/ToolAngling_Remake_4_0.png","variation":"Purple","filename":"ToolAngling_Remake_4_0","variantId":"4_0","uniqueEntryId":"PBLScat4po99B5h4k","colors":[],"bodyTitle":"Color","source":["Crafting"],"internalId":2377,"buy":-1,"sell":600,"themes":[]},{"image":"https://acnhcdn.com/latest/FtrIcon/ToolAngling_Remake_5_0.png","variation":"Pink","filename":"ToolAngling_Remake_5_0","variantId":"5_0","uniqueEntryId":"9bT9ZRhRG3e3WA8Bn","colors":[],"bodyTitle":"Color","source":["Crafting"],"internalId":2377,"buy":-1,"sell":600,"themes":[]},{"image":"https://acnhcdn.com/latest/FtrIcon/ToolAngling_Remake_6_0.png","variation":"White","filename":"ToolAngling_Remake_6_0","variantId":"6_0","uniqueEntryId":"G58mfRs22f48nF9QA","colors":[],"bodyTitle":"Color","source":["Crafting"],"internalId":2377,"buy":-1,"sell":600,"themes":[]},{"image":"https://acnhcdn.com/latest/FtrIcon/ToolAngling_Remake_7_0.png","variation":"Black","filename":"ToolAngling_Remake_7_0","variantId":"7_0","uniqueEntryId":"bgrXEg4NvgPjudWar","colors":[],"bodyTitle":"Color","source":["Crafting"],"internalId":2377,"buy":-1,"sell":600,"themes":[]}]}