{"sourceSheet":"Headwear","name":"silk hat","diy":false,"hhaBasePoints":451,"size":"1x1","exchangePrice":null,"exchangeCurrency":null,"sourceNotes":null,"seasonEvent":null,"seasonEventExclusive":null,"seasonalAvailability":"All Year","seasonality":"All Year","mannequinSeason":null,"gender":"Free","villagerGender":"Free","style1":"Elegant","style2":"Gorgeous","sortOrder":1,"type":"HeadCap","villagerEquippable":true,"catalog":"Not for sale","versionAdded":"1.0.0","unlocked":true,"clothGroupId":647,"variants":[{"variation":"Black","filename":"CapHatChina3","uniqueEntryId":"wAXG8RJJ7TpyncmcF","colors":["Red","Black"],"source":["Gulliver"],"closetImage":"https://acnhcdn.com/latest/ClosetIcon/CapHatChina3.png","storageImage":"https://acnhcdn.com/latest/FtrIcon/CapHatChina3.png","internalId":11851,"labelThemes":["everyday","formal"],"buy":-1,"sell":500,"themes":[]},{"variation":"Yellow","filename":"CapHatChina2","uniqueEntryId":"aSwkTGeBh4yrwfxAR","colors":["Red","Yellow"],"source":["Gulliver"],"closetImage":"https://acnhcdn.com/latest/ClosetIcon/CapHatChina2.png","storageImage":"https://acnhcdn.com/latest/FtrIcon/CapHatChina2.png","internalId":11850,"labelThemes":["everyday","formal"],"buy":-1,"sell":500,"themes":[]},{"variation":"Green","filename":"CapHatChina0","uniqueEntryId":"CCWstWanNNy9NeknS","colors":["Red","Green"],"source":["Gulliver"],"closetImage":"https://acnhcdn.com/latest/ClosetIcon/CapHatChina0.png","storageImage":"https://acnhcdn.com/latest/FtrIcon/CapHatChina0.png","internalId":5284,"labelThemes":["everyday","formal"],"buy":-1,"sell":500,"themes":[]},{"variation":"Blue","filename":"CapHatChina1","uniqueEntryId":"xPsEvMLiWZMoK6oGz","colors":["Red","Blue"],"source":["Gulliver"],"closetImage":"https://acnhcdn.com/latest/ClosetIcon/CapHatChina1.png","storageImage":"https://acnhcdn.com/latest/FtrIcon/CapHatChina1.png","internalId":11849,"labelThemes":["everyday","formal"],"buy":-1,"sell":500,"themes":[]}]}