{"sourceSheet":"Rugs","name":"dark bamboo rug","diy":true,"size":"3x2","sizeCategory":"Medium","exchangePrice":null,"exchangeCurrency":null,"sourceNotes":null,"seasonEvent":null,"seasonEventExclusive":null,"hhaBasePoints":103,"tag":"Wood Rugs","catalog":"Not for sale","versionAdded":"1.0.0","unlocked":true,"series":null,"variants":[{"image":"https://acnhcdn.com/latest/FtrIcon/RugRectBambooM01.png","filename":"RugRectBambooM01","uniqueEntryId":"yC3qR56GTSs3PZuJi","colors":["Brown","Brown"],"source":["Crafting"],"internalId":11114,"buy":-1,"sell":960,"themes":["zen-style"]}]}