{"sourceSheet":"Wall-mounted","name":"party garland","patternTitle":null,"diy":false,"patternCustomize":false,"kitType":null,"exchangePrice":null,"exchangeCurrency":null,"size":"2x1","sourceNotes":"Available in Nook's Cranny (either upgrade tier) in the unique furniture slot","seasonEvent":null,"seasonEventExclusive":null,"hhaBasePoints":151,"hhaCategory":null,"interact":false,"tag":"Seasonal Decor","outdoor":false,"lightingType":null,"doorDeco":false,"catalog":"For sale","versionAdded":"1.0.0","unlocked":true,"set":null,"series":null,"customizationKitCost":null,"variants":[{"image":"https://acnhcdn.com/latest/FtrIcon/FtrPartydecorationWall_Remake_0_0.png","variation":"Colorful","filename":"FtrPartydecorationWall_Remake_0_0","variantId":"0_0","uniqueEntryId":"Fhbeq58ZicAdCR5DF","colors":["Colorful","Colorful"],"pattern":null,"bodyCustomize":false,"bodyTitle":null,"source":["Nook's Cranny"],"internalId":4077,"buy":650,"sell":162,"themes":["party","fancy"]},{"image":"https://acnhcdn.com/latest/FtrIcon/FtrPartydecorationWall_Remake_1_0.png","variation":"Pastel","filename":"FtrPartydecorationWall_Remake_1_0","variantId":"1_0","uniqueEntryId":"Ses2wMLx4htuB5xAe","colors":["Colorful","Colorful"],"pattern":null,"bodyCustomize":false,"bodyTitle":null,"source":["Nook's Cranny"],"internalId":4077,"buy":650,"sell":162,"themes":["party","fancy"]},{"image":"https://acnhcdn.com/latest/FtrIcon/FtrPartydecorationWall_Remake_2_0.png","variation":"Boating stripes","filename":"FtrPartydecorationWall_Remake_2_0","variantId":"2_0","uniqueEntryId":"5QreLwE762koi732M","colors":["Aqua","White"],"pattern":null,"bodyCustomize":false,"bodyTitle":null,"source":["Nook's Cranny"],"internalId":4077,"buy":650,"sell":162,"themes":["party","fancy"]},{"image":"https://acnhcdn.com/latest/FtrIcon/FtrPartydecorationWall_Remake_3_0.png","variation":"Orange & black","filename":"FtrPartydecorationWall_Remake_3_0","variantId":"3_0","uniqueEntryId":"Yeg449pjrisRJ3FZE","colors":["Orange","Black"],"pattern":null,"bodyCustomize":false,"bodyTitle":null,"source":["Nook's Cranny"],"internalId":4077,"buy":650,"sell":162,"themes":["party","fancy"]},{"image":"https://acnhcdn.com/latest/FtrIcon/FtrPartydecorationWall_Remake_4_0.png","variation":"Pop","filename":"FtrPartydecorationWall_Remake_4_0","variantId":"4_0","uniqueEntryId":"B4Dib3e8XPEKr5An8","colors":["Green","Red"],"pattern":null,"bodyCustomize":false,"bodyTitle":null,"source":["Nook's Cranny"],"internalId":4077,"buy":650,"sell":162,"themes":["party","fancy"]},{"image":"https://acnhcdn.com/latest/FtrIcon/FtrPartydecorationWall_Remake_5_0.png","variation":"Gorgeous","filename":"FtrPartydecorationWall_Remake_5_0","variantId":"5_0","uniqueEntryId":"5gYwyrjAM92JqXyRw","colors":["Black","Brown"],"pattern":null,"bodyCustomize":false,"bodyTitle":null,"source":["Nook's Cranny"],"internalId":4077,"buy":650,"sell":162,"themes":["party","fancy"]}]}